README.md
fastforms.py
setup.cfg
setup.py
fastforms.egg-info/PKG-INFO
fastforms.egg-info/SOURCES.txt
fastforms.egg-info/dependency_links.txt
fastforms.egg-info/requires.txt
fastforms.egg-info/top_level.txt